pyvipe/__init__.py
pyvipe/__main__.py
pyvipe/pyvipe.py
pyvipe/version.py
pyvipe-0.2.2.data/data/share/bash-completion/completions/vipe
pyvipe-0.2.2.data/data/share/zsh/site-functions/_vipe
pyvipe-0.2.2.dist-info/LICENSE
pyvipe-0.2.2.dist-info/METADATA
pyvipe-0.2.2.dist-info/WHEEL
pyvipe-0.2.2.dist-info/entry_points.txt
pyvipe-0.2.2.dist-info/top_level.txt
pyvipe-0.2.2.dist-info/RECORD
