Metadata-Version: 2.1
Name: pyvipe
Version: 0.2.2
Summary: edit pipe with your editor.
Home-page: https://github.com/Constantin1489/pyvipe
Author: Constantin Hong
Author-email: Constantin Hong <hongconstantin@gmail.com>
Maintainer: Constantin Hong
Maintainer-email: Constantin Hong <hongconstantin@gmail.com>
License: GNU GENERAL PUBLIC LICENSE
Project-URL: Homepage, https://github.com/Constantin1489/pyvipe
Project-URL: Bug Tracker, https://github.com/Constantin1489/pyvipe/issues
Project-URL: Documentation, https://github.com/Constantin1489/pyvipe#readme
Classifier: Development Status :: 3 - Alpha
Classifier: Environment :: Console
Classifier: Topic :: Utilities
Classifier: Operating System :: MacOS :: MacOS X
Classifier: Operating System :: POSIX :: Linux
Classifier: License :: OSI Approved :: GNU General Public License v2 (GPLv2)
Classifier: Programming Language :: Python
Classifier: Programming Language :: Python :: 3.9
Classifier: Programming Language :: Python :: 3.10
Classifier: Programming Language :: Python :: 3.11
Requires-Python: >=3.9
License-File: LICENSE
